dprox/__init__.py
dprox/algo/__init__.py
dprox/algo/admm.py
dprox/algo/base.py
dprox/algo/hqs.py
dprox/algo/invert.py
dprox/algo/pc.py
dprox/algo/pgd.py
dprox/algo/primitives.py
dprox/algo/problem.py
dprox/algo/lp/__init__.py
dprox/algo/lp/solvers.py
dprox/algo/lp/utils.py
dprox/algo/opt/__init__.py
dprox/algo/opt/absorb.py
dprox/algo/opt/equil.py
dprox/algo/opt/merge.py
dprox/algo/specialization/__init__.py
dprox/algo/specialization/unroll.py
dprox/algo/specialization/deq/__init__.py
dprox/algo/specialization/deq/solver.py
dprox/algo/specialization/deq/training.py
dprox/algo/specialization/deq/utils/__init__.py
dprox/algo/specialization/deq/utils/jacobian.py
dprox/algo/specialization/deq/utils/layer_utils.py
dprox/algo/specialization/deq/utils/optimizations.py
dprox/algo/specialization/deq/utils/radam.py
dprox/algo/specialization/deq/utils/solvers.py
dprox/algo/specialization/rl/__init__.py
dprox/algo/specialization/rl/solver.py
dprox/algo/tune/__init__.py
dprox/algo/tune/dpir.py
dprox/algo/tune/learnable.py
dprox/contrib/__init__.py
dprox/contrib/csmri.py
dprox/contrib/derain.py
dprox/contrib/energy_system.py
dprox/contrib/restoration.py
dprox/contrib/optic/__init__.py
dprox/contrib/optic/doe_model.py
dprox/contrib/optic/unet.py
dprox/contrib/optic/utils.py
dprox/linalg/__init__.py
dprox/linalg/custom.py
dprox/linalg/solve/__init__.py
dprox/linalg/solve/solver_cg.py
dprox/linalg/solve/solver_minres.py
dprox/linalg/solve/solver_plss.py
dprox/linop/__init__.py
dprox/linop/base.py
dprox/linop/blackbox.py
dprox/linop/comp_graph.py
dprox/linop/constaints.py
dprox/linop/constant.py
dprox/linop/conv.py
dprox/linop/edge.py
dprox/linop/grad.py
dprox/linop/mul.py
dprox/linop/placeholder.py
dprox/linop/scale.py
dprox/linop/subsample.py
dprox/linop/sum.py
dprox/linop/variable.py
dprox/linop/vstack.py
dprox/proxfn/__init__.py
dprox/proxfn/base.py
dprox/proxfn/nonneg.py
dprox/proxfn/norm.py
dprox/proxfn/sum_square.py
dprox/proxfn/fast/__init__.py
dprox/proxfn/fast/cs.py
dprox-0.2.1.dist-info/METADATA
dprox-0.2.1.dist-info/WHEEL
dprox-0.2.1.dist-info/top_level.txt
dprox-0.2.1.dist-info/RECORD
