Metadata-Version: 2.1
Name: dprox
Version: 0.2.1
Summary: A domain-specific language and compiler that transforms optimization problems into differentiable proximal solvers.
Home-page: https://github.com/princeton-computational-imaging/Delta-Prox
Author: Zeqiang Lai
Author-email: laizeqiang@outlook.com
Requires-Dist: imageio
Requires-Dist: scikit-image
Requires-Dist: matplotlib
Requires-Dist: munch
Requires-Dist: tfpnp
Requires-Dist: cvxpy
Requires-Dist: torchlights
Requires-Dist: tensorboardX
Requires-Dist: termcolor
Requires-Dist: proximal
Requires-Dist: opencv-python
Requires-Dist: huggingface-hub
